soccer_player-0.2.1.dist-info/METADATA
soccer_player-0.2.1.dist-info/WHEEL
soccer_player/.forward.py.swo
soccer_player/.pytest_cache/.gitignore
soccer_player/.pytest_cache/CACHEDIR.TAG
soccer_player/.pytest_cache/README.md
soccer_player/.pytest_cache/v/cache/nodeids
soccer_player/.pytest_cache/v/cache/stepwise
soccer_player/__init__.py
soccer_player/forward.py
soccer_player-0.2.1.dist-info/RECORD
