Metadata-Version: 2.1
Name: soccer-player
Version: 0.2.1
Summary: demonstrates players' records
Author-Email: junsungs950 <junsungs950@gmail.com>
License: MIT
Requires-Python: >=3.9
